fetchmgs/__init__.py
fetchmgs/fetchmgs.py
fetchmgs/data/COG0012.hmm
fetchmgs/data/COG0016.hmm
fetchmgs/data/COG0018.hmm
fetchmgs/data/COG0048.hmm
fetchmgs/data/COG0049.hmm
fetchmgs/data/COG0052.hmm
fetchmgs/data/COG0080.hmm
fetchmgs/data/COG0081.hmm
fetchmgs/data/COG0085.hmm
fetchmgs/data/COG0086.hmm
fetchmgs/data/COG0087.hmm
fetchmgs/data/COG0088.hmm
fetchmgs/data/COG0090.hmm
fetchmgs/data/COG0091.hmm
fetchmgs/data/COG0092.hmm
fetchmgs/data/COG0093.hmm
fetchmgs/data/COG0094.hmm
fetchmgs/data/COG0096.hmm
fetchmgs/data/COG0097.hmm
fetchmgs/data/COG0098.hmm
fetchmgs/data/COG0099.hmm
fetchmgs/data/COG0100.hmm
fetchmgs/data/COG0102.hmm
fetchmgs/data/COG0103.hmm
fetchmgs/data/COG0124.hmm
fetchmgs/data/COG0172.hmm
fetchmgs/data/COG0184.hmm
fetchmgs/data/COG0185.hmm
fetchmgs/data/COG0186.hmm
fetchmgs/data/COG0197.hmm
fetchmgs/data/COG0200.hmm
fetchmgs/data/COG0201.hmm
fetchmgs/data/COG0202.hmm
fetchmgs/data/COG0215.hmm
fetchmgs/data/COG0256.hmm
fetchmgs/data/COG0495.hmm
fetchmgs/data/COG0522.hmm
fetchmgs/data/COG0525.hmm
fetchmgs/data/COG0533.hmm
fetchmgs/data/COG0541.hmm
fetchmgs/data/COG0552.hmm
fetchmgs/data/MG_BitScoreCutoffs.allhits.txt
fetchmgs/data/MG_BitScoreCutoffs.uncalibrated.txt
fetchmgs/data/MG_BitScoreCutoffs.verybesthit.txt
fetchmgs-2.1.0.dist-info/licenses/LICENSE
fetchmgs-2.1.0.dist-info/METADATA
fetchmgs-2.1.0.dist-info/WHEEL
fetchmgs-2.1.0.dist-info/entry_points.txt
fetchmgs-2.1.0.dist-info/top_level.txt
fetchmgs-2.1.0.dist-info/RECORD
