Metadata-Version: 2.4
Name: fetchMGs
Version: 2.1.0
Summary: FetchMGs extracts the 40 marker genes from genomes and metagenomes in an easy and accurate manner.
Home-page: https://github.com/motu-tool/FetchMGs
Download-URL: https://github.com/motu-tool/FetchMGs/archive/refs/tags/2.1.0.tar.gz
Author: Hans-Joachim Ruscheweyh, Chris Field, Shinichi Sunagawa, Daniel R. Mende
Author-email: hansr@ethz.ch
License: GPL-3.0
Classifier: Programming Language :: Python
Classifier: Programming Language :: Python :: 3
Classifier: Development Status :: 5 - Production/Stable
Classifier: Intended Audience :: Science/Research
Classifier: Topic :: Scientific/Engineering :: Bio-Informatics
Classifier: License :: OSI Approved :: GNU General Public License v3 (GPLv3)
Classifier: Operating System :: OS Independent
License-File: LICENSE
Requires-Dist: biopython
Requires-Dist: tqdm
Requires-Dist: pyrodigal==3.6.3
Requires-Dist: pyhmmer==0.10.15
Requires-Dist: psutil
Dynamic: author
Dynamic: author-email
Dynamic: classifier
Dynamic: description
Dynamic: description-content-type
Dynamic: download-url
Dynamic: home-page
Dynamic: license
Dynamic: license-file
Dynamic: requires-dist
Dynamic: summary
